postbin/__init__.py
postbin/__main__.py
postbin/v2/__init__.py
postbin/v2/errors.py
PostBin-1.2.0.dist-info/LICENSE
PostBin-1.2.0.dist-info/METADATA
PostBin-1.2.0.dist-info/WHEEL
PostBin-1.2.0.dist-info/top_level.txt
PostBin-1.2.0.dist-info/RECORD
