Metadata-Version: 2.1
Name: PostBin
Version: 1.2.0
Summary: A simple two-function program that POSTs to hastebin
Home-page: https://github.com/dragdev-studios/postbin
Author: EEKIM10
Author-email: eek@clicksminuteper.net
License: MIT
Platform: UNKNOWN
Requires-Python: >=3.6
Provides-Extra: cli
